simple_pkg/__init__.py
simple_pkg_by_zxz/__init__.py
simple_pkg_by_zxz-0.1.0.dist-info/LICENSE
simple_pkg_by_zxz-0.1.0.dist-info/METADATA
simple_pkg_by_zxz-0.1.0.dist-info/WHEEL
simple_pkg_by_zxz-0.1.0.dist-info/top_level.txt
simple_pkg_by_zxz-0.1.0.dist-info/RECORD
