Metadata-Version: 2.1
Name: simple-pkg-by-zxz
Version: 0.1.0
Summary: A simple greeting package
Home-page: https://github.com/yourusername/simple_pkg
Author: Your Name
Author-email: your.email@example.com
License: MIT
Classifier: Programming Language :: Python :: 3
Classifier: License :: OSI Approved :: MIT License
Classifier: Operating System :: OS Independent
License-File: LICENSE
